codestructure.py
codestructure-1.1.0.dist-info/LICENSE
codestructure-1.1.0.dist-info/METADATA
codestructure-1.1.0.dist-info/WHEEL
codestructure-1.1.0.dist-info/entry_points.txt
codestructure-1.1.0.dist-info/top_level.txt
codestructure-1.1.0.dist-info/RECORD
