Metadata-Version: 2.1
Name: codestructure
Version: 1.1.0
Summary: CodeStructure is a Python package that analyzes the structure of a Python file and extracts information about its classes, functions, and their associated attributes.
Author-email: Bas Nijholt <bas@nijho.lt>
License: Apache License
Project-URL: Homepage, https://github.com/basnijholt/codestructure
Requires-Python: >=3.10
License-File: LICENSE
Requires-Dist: pyperclip
Requires-Dist: rich
Provides-Extra: docs
Requires-Dist: pandas ; extra == 'docs'
Requires-Dist: tabulate ; extra == 'docs'
Requires-Dist: tqdm ; extra == 'docs'
Provides-Extra: test
Requires-Dist: pytest ; extra == 'test'
Requires-Dist: pre-commit ; extra == 'test'
Requires-Dist: coverage ; extra == 'test'
Requires-Dist: pytest-cov ; extra == 'test'
